{
  "country": "Saudi Arabia",
  "last_updated": "2026-04-25T11:36:51.475359+00:00",
  "story_count": 70,
  "stories": [
    {
      "title": "Saudi Crown Prince, Zelensky discuss Ukraine crisis and Middle East in Jeddah talks",
      "source": "Saudi Gazette",
      "url": "https://saudigazette.com.sa/article/660821/saudi-arabia/saudi-crown-prince-and-zelensky-discuss-ukraine-crisis-in-jeddah",
      "published_date": "2026-04-24T19:32:12+00:00",
      "category": "Diplomacy"
    },
    {
      "title": "Public Prosecution approves remote work, anti-fraud office in reform push",
      "source": "Saudi Gazette",
      "url": "https://saudigazette.com.sa/article/660818/saudi-arabia/saudi-public-prosecution-approves-remote-work-and-anti-fraud-office",
      "published_date": "2026-04-24T15:36:04+00:00",
      "category": "Diplomacy"
    },
    {
      "title": "Saudi Arabia, Switzerland sign investment pact as leaders hold business forum in Jeddah",
      "source": "Saudi Gazette",
      "url": "https://saudigazette.com.sa/article/660804/saudi-arabia/saudi-arabia-switzerland-sign-investment-protection-pact-in-jeddah",
      "published_date": "2026-04-24T03:36:50+00:00",
      "category": "Diplomacy"
    },
    {
      "title": "Saudi FM, Lebanese speaker discuss efforts for cessation of Israeli hostilities in phone call",
      "source": "Saudi Gazette",
      "url": "https://saudigazette.com.sa/article/660797/saudi-arabia/saudi-fm-lebanese-speaker-discuss-efforts-for-cessation-of-israeli-hostilities-in-phone-call",
      "published_date": "2026-04-23T19:59:10+00:00",
      "category": "Diplomacy"
    },
    {
      "title": "Council of Health Insurance slaps SR4 million fines on violating employers",
      "source": "Saudi Gazette",
      "url": "https://saudigazette.com.sa/article/660796/saudi-arabia/council-of-health-insurance-slaps-sr4-million-fines-on-violating-employers",
      "published_date": "2026-04-23T17:00:04+00:00",
      "category": "Diplomacy"
    },
    {
      "title": "Saudi, Cuban FMs discuss Mideast situation in phone call",
      "source": "Saudi Gazette",
      "url": "https://saudigazette.com.sa/article/660794/saudi-arabia/saudi-cuban-fms-discuss-mideast-situation-in-phone-call",
      "published_date": "2026-04-23T15:53:44+00:00",
      "category": "Diplomacy"
    },
    {
      "title": "Saudi surgeons begin 24-hour separation of Filipino conjoined twins in one of world’s most complex cases",
      "source": "Saudi Gazette",
      "url": "https://saudigazette.com.sa/article/660783/saudi-arabia/saudi-surgeons-begin-separation-of-filipino-conjoined-twins-in-riyadh",
      "published_date": "2026-04-23T12:44:03+00:00",
      "category": "Diplomacy"
    },
    {
      "title": "Saudi Crown Prince, Swiss president discuss expanding investment ties in Jeddah meeting",
      "source": "Saudi Gazette",
      "url": "https://saudigazette.com.sa/article/660779/saudi-arabia/saudi-crown-prince-meets-swiss-president-in-jeddah-to-boost-investment-ties",
      "published_date": "2026-04-23T11:52:09+00:00",
      "category": "Diplomacy"
    },
    {
      "title": "Crown Prince, Japan PM discuss regional tensions, maritime supply concerns",
      "source": "Saudi Gazette",
      "url": "https://saudigazette.com.sa/article/660775/saudi-arabia/crown-prince-japan-pm-discuss-regional-tensions-maritime-supply-concerns",
      "published_date": "2026-04-23T10:58:58+00:00",
      "category": "Diplomacy"
    },
    {
      "title": "Saudi, Dutch FMs discuss efforts for safety of international waterways",
      "source": "Saudi Gazette",
      "url": "https://saudigazette.com.sa/article/660768/saudi-arabia/saudi-dutch-fms-discuss-efforts-for-safety-of-international-waterways",
      "published_date": "2026-04-22T20:42:42+00:00",
      "category": "Diplomacy"
    },
    {
      "title": "Saudi construction costs rise by 2% in March",
      "source": "Saudi Gazette",
      "url": "https://saudigazette.com.sa/article/660765/saudi-arabia/saudi-construction-costs-rise-by-2-in-march",
      "published_date": "2026-04-22T16:56:21+00:00",
      "category": "Diplomacy"
    },
    {
      "title": "Saudi space mission reveals key gene changes in cells, opening path to advanced medicine",
      "source": "Saudi Gazette",
      "url": "https://saudigazette.com.sa/article/660761/saudi-arabia/saudi-space-mission-reveals-key-gene-changes-in-cells-opening-path-to-advanced-medicine",
      "published_date": "2026-04-22T15:15:27+00:00",
      "category": "Diplomacy"
    },
    {
      "title": "Trump buys time for Iran deal after frantic day of diplomacy",
      "source": "BBC News",
      "url": "https://www.bbc.com/news/articles/cvg4yr90jr2o?at_medium=RSS&at_campaign=rss",
      "published_date": "2026-04-22T00:32:10+00:00",
      "category": "Diplomacy"
    },
    {
      "title": "Aoun thanks for continued Saudi support to Lebanon in call with Crown Prince",
      "source": "Saudi Gazette",
      "url": "https://saudigazette.com.sa/article/660741/saudi-arabia/aoun-thanks-for-continued-saudi-support-to-lebanon-in-call-with-crown-prince",
      "published_date": "2026-04-21T21:06:59+00:00",
      "category": "Diplomacy"
    },
    {
      "title": "Saudi Crown Prince, Syrian President discuss regional developments in Jeddah",
      "source": "Saudi Gazette",
      "url": "https://saudigazette.com.sa/article/660740/saudi-arabia/saudi-crown-prince-syrian-president-discuss-regional-developments-in-jeddah",
      "published_date": "2026-04-21T20:35:41+00:00",
      "category": "Diplomacy"
    },
    {
      "title": "Absher carries out over 43.5 million electronic transactions in March",
      "source": "Saudi Gazette",
      "url": "https://saudigazette.com.sa/article/660732/saudi-arabia/absher-carries-out-over-435-million-electronic-transactions-in-march",
      "published_date": "2026-04-21T14:16:01+00:00",
      "category": "Diplomacy"
    },
    {
      "title": "King Salman and Crown Prince congratulate new Iraqi President Nizar Amidi",
      "source": "Saudi Gazette",
      "url": "https://saudigazette.com.sa/article/660730/saudi-arabia/king-salman-and-crown-prince-congratulate-new-iraqi-president-nizar-amidi",
      "published_date": "2026-04-21T13:45:44+00:00",
      "category": "Diplomacy"
    },
    {
      "title": "Saudi FM holds talks with Kuwait, Oman counterparts on regional security",
      "source": "Saudi Gazette",
      "url": "https://saudigazette.com.sa/article/660724/saudi-arabia/saudi-fm-holds-talks-with-kuwait-oman-counterparts-on-regional-security",
      "published_date": "2026-04-21T11:32:34+00:00",
      "category": "Diplomacy"
    },
    {
      "title": "Saudi Arabia reaffirms full support for Palestinian government’s reform program",
      "source": "Saudi Gazette",
      "url": "https://saudigazette.com.sa/article/660710/saudi-arabia/saudi-arabia-reaffirms-full-support-for-palestinian-governments-reform-program",
      "published_date": "2026-04-20T20:51:25+00:00",
      "category": "Diplomacy"
    },
    {
      "title": "Saudi Crown Prince, Al-Burhan discuss safeguarding Sudan’s security and sovereignty",
      "source": "Saudi Gazette",
      "url": "https://saudigazette.com.sa/article/660707/saudi-arabia/saudi-crown-prince-al-burhan-discuss-safeguarding-sudans-security-and-sovereignty",
      "published_date": "2026-04-20T16:52:23+00:00",
      "category": "Diplomacy"
    },
    {
      "title": "Saudi customs foils attempt to smuggle 154,108 Captagon pills at Al Haditha border",
      "source": "Saudi Gazette",
      "url": "https://saudigazette.com.sa/article/660819/saudi-arabia/saudi-customs-foils-smuggling-of-154108-captagon-pills-at-al-haditha-border",
      "published_date": "2026-04-24T16:06:02+00:00",
      "category": "Military"
    },
    {
      "title": "Key suspect in notorious Tadamon massacre during Syria civil war arrested",
      "source": "BBC News",
      "url": "https://www.bbc.com/news/articles/cvglxgq1p2jo?at_medium=RSS&at_campaign=rss",
      "published_date": "2026-04-24T10:41:32+00:00",
      "category": "Military"
    },
    {
      "title": "US-Kuwaiti journalist held in Kuwait over social media posts acquitted, lawyers say",
      "source": "BBC News",
      "url": "https://www.bbc.com/news/articles/cy81ljrd445o?at_medium=RSS&at_campaign=rss",
      "published_date": "2026-04-23T15:11:03+00:00",
      "category": "Military"
    },
    {
      "title": "Lebanon accuses Israel of targeting journalist killed in air strike",
      "source": "BBC News",
      "url": "https://www.bbc.com/news/articles/c5yvn036evlo?at_medium=RSS&at_campaign=rss",
      "published_date": "2026-04-23T04:25:30+00:00",
      "category": "Military"
    },
    {
      "title": "Six categories are permitted to enter Makkah with an Absher permit",
      "source": "Saudi Gazette",
      "url": "https://saudigazette.com.sa/article/660764/saudi-arabia/six-categories-are-permitted-to-enter-makkah-with-an-absher-permit",
      "published_date": "2026-04-22T16:28:32+00:00",
      "category": "Military"
    },
    {
      "title": "Saudi, Italian defense ministers discuss enhancing military partnership",
      "source": "Saudi Gazette",
      "url": "https://saudigazette.com.sa/article/660759/saudi-arabia/saudi-italian-defense-ministers-discuss-enhancing-military-partnership",
      "published_date": "2026-04-22T14:23:05+00:00",
      "category": "Military"
    },
    {
      "title": "US and Iran 'locked in war of words' says Lyse Doucet",
      "source": "BBC News",
      "url": "https://www.bbc.com/news/videos/cvg3yxkrd0po?at_medium=RSS&at_campaign=rss",
      "published_date": "2026-04-22T08:37:50+00:00",
      "category": "Military"
    },
    {
      "title": "UAE-backed Colombian mercenaries provided support to Sudan paramilitary, report says",
      "source": "BBC News",
      "url": "https://www.bbc.com/news/articles/cn4vk13wgwwo?at_medium=RSS&at_campaign=rss",
      "published_date": "2026-04-22T04:01:50+00:00",
      "category": "Military"
    },
    {
      "title": "Two Palestinians killed during settler attack on West Bank village, officials say",
      "source": "BBC News",
      "url": "https://www.bbc.com/news/articles/cp864d661rro?at_medium=RSS&at_campaign=rss",
      "published_date": "2026-04-21T17:17:33+00:00",
      "category": "Military"
    },
    {
      "title": "Israeli soldiers punished over vandalism of Jesus statue in Lebanon",
      "source": "BBC News",
      "url": "https://www.bbc.com/news/articles/cew790ppn8jo?at_medium=RSS&at_campaign=rss",
      "published_date": "2026-04-21T16:13:27+00:00",
      "category": "Military"
    },
    {
      "title": "Iran sees mass redundancies from war with US and Israel",
      "source": "BBC News",
      "url": "https://www.bbc.com/news/articles/ce84e31376zo?at_medium=RSS&at_campaign=rss",
      "published_date": "2026-04-21T16:05:51+00:00",
      "category": "Military"
    },
    {
      "title": "'Nothing to go back to' - BBC reports from Lebanon's 'Yellow Line'",
      "source": "BBC News",
      "url": "https://www.bbc.com/news/videos/cj37dj76njno?at_medium=RSS&at_campaign=rss",
      "published_date": "2026-04-21T14:12:59+00:00",
      "category": "Military"
    },
    {
      "title": "Saudi authority launches service to check crowd levels in tawaf and sa’i areas at Grand Mosque",
      "source": "Saudi Gazette",
      "url": "https://saudigazette.com.sa/article/660731/saudi-arabia/saudi-arabia-launches-live-crowd-tracking-service-for-grand-mosque-pilgrims",
      "published_date": "2026-04-21T14:09:11+00:00",
      "category": "Military"
    },
    {
      "title": "Saudi Arabia backs UAE after foiled terror plot",
      "source": "Saudi Gazette",
      "url": "https://saudigazette.com.sa/article/660727/saudi-arabia/saudi-arabia-supports-uae-after-foiled-terror-plot-linked-to-iran",
      "published_date": "2026-04-21T12:56:52+00:00",
      "category": "Military"
    },
    {
      "title": "Deputy defense minister attends graduation ceremony of 84th batch of King Abdulaziz Military Academy cadets",
      "source": "Saudi Gazette",
      "url": "https://saudigazette.com.sa/article/660711/saudi-arabia/deputy-defense-minister-attends-graduation-ceremony-of-84th-batch-of-king-abdulaziz-military-academy-cadets",
      "published_date": "2026-04-20T21:16:05+00:00",
      "category": "Military"
    },
    {
      "title": "Outrage over Israeli soldier's vandalism of Jesus statue in Lebanon",
      "source": "BBC News",
      "url": "https://www.bbc.com/news/articles/cpd575n1znzo?at_medium=RSS&at_campaign=rss",
      "published_date": "2026-04-20T18:57:25+00:00",
      "category": "Military"
    },
    {
      "title": "Are insider traders making millions from the Iran war?",
      "source": "BBC News",
      "url": "https://www.bbc.com/news/videos/c9qd9335838o?at_medium=RSS&at_campaign=rss",
      "published_date": "2026-04-20T12:14:56+00:00",
      "category": "Military"
    },
    {
      "title": "Holy Kaaba maintenance completed with highest global standards",
      "source": "Saudi Gazette",
      "url": "https://saudigazette.com.sa/article/660647/saudi-arabia/holy-kaaba-maintenance-completed-with-highest-global-standards",
      "published_date": "2026-04-18T16:48:46+00:00",
      "category": "Military"
    },
    {
      "title": "French peacekeeper killed in southern Lebanon",
      "source": "BBC News",
      "url": "https://www.bbc.com/news/articles/cvg4mrm2vm0o?at_medium=RSS&at_campaign=rss",
      "published_date": "2026-04-18T14:53:17+00:00",
      "category": "Military"
    },
    {
      "title": "Saudi Arabia among 10 countries welcoming Libya’s unified budget agreement",
      "source": "Saudi Gazette",
      "url": "https://saudigazette.com.sa/article/660683/saudi-arabia/saudi-arabia-among-10-countries-welcoming-libyas-unified-budget-agreement",
      "published_date": "2026-04-19T21:30:16+00:00",
      "category": "Energy"
    },
    {
      "title": "Saudi sukuk added to J.P. Morgan and Bloomberg emerging market bond indices",
      "source": "Saudi Gazette",
      "url": "https://saudigazette.com.sa/article/660817/saudi-arabia/saudi-sukuk-added-to-jp-morgan-and-bloomberg-emerging-market-bond-indices",
      "published_date": "2026-04-24T14:57:14+00:00",
      "category": "Economy"
    },
    {
      "title": "Health minister inspects Makkah medical facilities, ensures full readiness for Hajj 2026",
      "source": "Saudi Gazette",
      "url": "https://saudigazette.com.sa/article/660800/saudi-arabia/health-minister-inspects-makkah-medical-facilities-ensures-full-readiness-for-hajj-2026",
      "published_date": "2026-04-23T21:00:44+00:00",
      "category": "Economy"
    },
    {
      "title": "Saudi Arabia secures leading GEM rankings, reinforcing its position as premier global entrepreneurship hub",
      "source": "Saudi Gazette",
      "url": "https://saudigazette.com.sa/article/660792/saudi-arabia/saudi-arabia-secures-leading-gem-rankings-reinforcing-its-position-as-premier-global-entrepreneurship-hub",
      "published_date": "2026-04-23T14:57:19+00:00",
      "category": "Economy"
    },
    {
      "title": "Crown Prince calls for all-out efforts to ensure seamless Hajj operation",
      "source": "Saudi Gazette",
      "url": "https://saudigazette.com.sa/article/660739/saudi-arabia/crown-prince-calls-for-all-out-efforts-to-ensure-seamless-hajj-operation",
      "published_date": "2026-04-21T19:33:37+00:00",
      "category": "Economy"
    },
    {
      "title": "Saudi FDI inflows top SR1 trillion in 2025, up 13%",
      "source": "Saudi Gazette",
      "url": "https://saudigazette.com.sa/article/660725/saudi-arabia/saudi-fdi-rises-13-to-surpass-sr1-trillion-in-2025",
      "published_date": "2026-04-21T12:14:19+00:00",
      "category": "Economy"
    },
    {
      "title": "Saudi liquidity surges 8.4% to SR3.28 trillion by end of February 2026",
      "source": "Saudi Gazette",
      "url": "https://saudigazette.com.sa/article/660708/saudi-arabia/saudi-liquidity-surges-84-to-sr328-trillion-by-end-of-february-2026",
      "published_date": "2026-04-20T17:28:51+00:00",
      "category": "Economy"
    },
    {
      "title": "Saudi Arabia signs Expo Belgrade 2027 participation deal, moves into execution phase",
      "source": "Saudi Gazette",
      "url": "https://saudigazette.com.sa/article/660692/saudi-arabia/saudi-arabia-signs-expo-belgrade-2027-participation-deal-moves-into-execution-phase",
      "published_date": "2026-04-20T11:59:52+00:00",
      "category": "Economy"
    },
    {
      "title": "60% Saudization in 20 marketing and sales professions begins as grace period comes to an end",
      "source": "Saudi Gazette",
      "url": "https://saudigazette.com.sa/article/660664/saudi-arabia/60-saudization-in-20-marketing-and-sales-professions-begins-as-grace-period-comes-to-an-end",
      "published_date": "2026-04-19T13:18:59+00:00",
      "category": "Economy"
    },
    {
      "title": "Port of NEOM fully operational, handling global cargo flows",
      "source": "Saudi Gazette",
      "url": "https://saudigazette.com.sa/article/660663/saudi-arabia/port-of-neom-fully-operational-handling-global-cargo-flows",
      "published_date": "2026-04-19T12:58:03+00:00",
      "category": "Economy"
    },
    {
      "title": "Saudi Arabia projected 3rd fastest-growing G20 economy in 2027: IMF",
      "source": "Saudi Gazette",
      "url": "https://saudigazette.com.sa/article/660662/saudi-arabia/saudi-arabia-projected-3rd-fastest-growing-g20-economy-in-2027-imf",
      "published_date": "2026-04-19T12:56:47+00:00",
      "category": "Economy"
    },
    {
      "title": "Palestinians in West Bank and some in Gaza vote in local elections",
      "source": "BBC News",
      "url": "https://www.bbc.com/news/articles/cn4vej3x0wxo?at_medium=RSS&at_campaign=rss",
      "published_date": "2026-04-25T10:52:27+00:00",
      "category": "Local Events"
    },
    {
      "title": "Israeli police investigate after officers 'cut Palestinian flag' from skullcap",
      "source": "BBC News",
      "url": "https://www.bbc.com/news/articles/cz67qjn48eqo?at_medium=RSS&at_campaign=rss",
      "published_date": "2026-04-24T16:20:10+00:00",
      "category": "Local Events"
    },
    {
      "title": "Heavy rain forecast for Riyadh through Monday",
      "source": "Saudi Gazette",
      "url": "https://saudigazette.com.sa/article/660814/saudi-arabia/saudi-arabia-warns-of-heavy-rain-in-riyadh-makkah-and-multiple-regions",
      "published_date": "2026-04-24T14:09:40+00:00",
      "category": "Local Events"
    },
    {
      "title": "Saudi surgeons complete separation of Filipino conjoined twins in 18.5-hour complex operation",
      "source": "Saudi Gazette",
      "url": "https://saudigazette.com.sa/article/660805/saudi-arabia/saudi-surgeons-complete-separation-of-filipino-conjoined-twins-in-riyadh",
      "published_date": "2026-04-24T05:38:03+00:00",
      "category": "Local Events"
    },
    {
      "title": "Saudi Arabia and 7 other Islamic nations denounce Israeli violations of Jerusalem’s Islamic and Christian holy sites",
      "source": "Saudi Gazette",
      "url": "https://saudigazette.com.sa/article/660801/saudi-arabia/saudi-arabia-and-7-other-islamic-nations-denounce-israeli-violations-of-jerusalems-islamic-and-christian-holy-sites",
      "published_date": "2026-04-23T21:46:24+00:00",
      "category": "Local Events"
    },
    {
      "title": "Civil Defense warns of continued thunderstorms across Saudi Arabia through Tuesday",
      "source": "Saudi Gazette",
      "url": "https://saudigazette.com.sa/article/660799/saudi-arabia/civil-defense-warns-of-continued-thunderstorms-across-saudi-arabia-through-tuesday",
      "published_date": "2026-04-23T20:56:33+00:00",
      "category": "Local Events"
    },
    {
      "title": "Interior Ministry: Up to SR100,000 fine for sheltering visit visa holders in Makkah during Hajj season",
      "source": "Saudi Gazette",
      "url": "https://saudigazette.com.sa/article/660798/saudi-arabia/interior-ministry-up-to-sr100000-fine-for-sheltering-visit-visa-holders-in-makkah-during-hajj-season",
      "published_date": "2026-04-23T20:10:16+00:00",
      "category": "Local Events"
    },
    {
      "title": "Over 19,000 inspection visits conducted to assess pilgrims’ housing compliance in Makkah, Madinah",
      "source": "Saudi Gazette",
      "url": "https://saudigazette.com.sa/article/660795/saudi-arabia/over-19000-inspection-visits-conducted-to-assess-pilgrims-housing-compliance-in-makkah-madinah",
      "published_date": "2026-04-23T16:37:57+00:00",
      "category": "Local Events"
    },
    {
      "title": "4 residents and a citizen arrested in Makkah for posting fake Hajj service ads",
      "source": "Saudi Gazette",
      "url": "https://saudigazette.com.sa/article/660791/saudi-arabia/4-residents-and-a-citizen-arrested-in-makkah-for-posting-fake-hajj-service-ads",
      "published_date": "2026-04-23T14:21:33+00:00",
      "category": "Local Events"
    },
    {
      "title": "Over 30.6 million passengers used urban public buses across Saudi Arabia in Q1 2026",
      "source": "Saudi Gazette",
      "url": "https://saudigazette.com.sa/article/660790/saudi-arabia/over-306-million-passengers-used-urban-public-buses-across-saudi-arabia-in-q1-2026",
      "published_date": "2026-04-23T13:53:21+00:00",
      "category": "Local Events"
    },
    {
      "title": "Attempt to smuggle over 2.7 million amphetamine pills foiled in Eastern Province",
      "source": "Saudi Gazette",
      "url": "https://saudigazette.com.sa/article/660787/saudi-arabia/attempt-to-smuggle-over-27-million-amphetamine-pills-foiled-in-eastern-province",
      "published_date": "2026-04-23T13:09:08+00:00",
      "category": "Local Events"
    },
    {
      "title": "SAR extends free storage at Riyadh dry port to 30 days",
      "source": "Saudi Gazette",
      "url": "https://saudigazette.com.sa/article/660786/saudi-arabia/sar-extends-free-storage-at-riyadh-dry-port-to-30-days",
      "published_date": "2026-04-23T13:04:10+00:00",
      "category": "Local Events"
    },
    {
      "title": "1,414 new archaeological sites registered in National Antiquities Register",
      "source": "Saudi Gazette",
      "url": "https://saudigazette.com.sa/article/660785/saudi-arabia/1414-new-archaeological-sites-registered-in-national-antiquities-register",
      "published_date": "2026-04-23T12:57:01+00:00",
      "category": "Local Events"
    },
    {
      "title": "Saudi digital readiness hits 76.04% as government accelerates emerging tech adoption",
      "source": "Saudi Gazette",
      "url": "https://saudigazette.com.sa/article/660778/saudi-arabia/saudi-digital-readiness-hits-7604-as-government-accelerates-emerging-tech-adoption",
      "published_date": "2026-04-23T11:37:12+00:00",
      "category": "Local Events"
    },
    {
      "title": "Israeli strike kills five Palestinians in northern Gaza, medics say",
      "source": "BBC News",
      "url": "https://www.bbc.com/news/articles/cly60dwxjd1o?at_medium=RSS&at_campaign=rss",
      "published_date": "2026-04-23T09:59:45+00:00",
      "category": "Local Events"
    },
    {
      "title": "Justice minister makes inspection tour of Jeddah courts",
      "source": "Saudi Gazette",
      "url": "https://saudigazette.com.sa/article/660769/saudi-arabia/justice-minister-makes-inspection-tour-of-jeddah-courts",
      "published_date": "2026-04-22T20:47:30+00:00",
      "category": "Local Events"
    },
    {
      "title": "Tracking ships under fire in the Strait of Hormuz",
      "source": "BBC News",
      "url": "https://www.bbc.com/news/videos/c1l93gg7zmno?at_medium=RSS&at_campaign=rss",
      "published_date": "2026-04-22T20:12:03+00:00",
      "category": "Local Events"
    },
    {
      "title": "Ride-hailing apps see 15.7% increase with 32 million trips in Q1 2026",
      "source": "Saudi Gazette",
      "url": "https://saudigazette.com.sa/article/660767/saudi-arabia/ride-hailing-apps-see-157-increase-with-32-million-trips-in-q1-2026",
      "published_date": "2026-04-22T17:29:41+00:00",
      "category": "Local Events"
    },
    {
      "title": "SFDA: 10-year jail and SR10 million fine for unauthorized food activities during Hajj",
      "source": "Saudi Gazette",
      "url": "https://saudigazette.com.sa/article/660766/saudi-arabia/sfda-10-year-jail-and-sr10-million-fine-for-unauthorized-food-activities-during-hajj",
      "published_date": "2026-04-22T17:25:46+00:00",
      "category": "Local Events"
    },
    {
      "title": "Hajj Security Forces arrest citizen and resident for transporting people to Makkah illegally",
      "source": "Saudi Gazette",
      "url": "https://saudigazette.com.sa/article/660763/saudi-arabia/hajj-security-forces-arrest-egyptian-resident-for-transporting-visa-holder-to-makkah-illegally",
      "published_date": "2026-04-22T15:39:12+00:00",
      "category": "Local Events"
    }
  ]
}